session_converter/__init__.py
session_converter/session.py
telegram_session_converter-0.1.1.dist-info/METADATA
telegram_session_converter-0.1.1.dist-info/WHEEL
telegram_session_converter-0.1.1.dist-info/top_level.txt
telegram_session_converter-0.1.1.dist-info/RECORD
