Metadata-Version: 2.1
Name: telegram-session-converter
Version: 0.1.1
Summary: A simple library for converting .session files from/to telethon or pyrogram format
Author: bundemshake
Author-email: bundemshake@gmail.com
Classifier: Programming Language :: Python :: 3
Classifier: License :: OSI Approved :: MIT License
Requires-Dist: telethon
Requires-Dist: pydantic
